preprocessing/__init__.py
preprocessing/preprocess.py
akshat_preprocessing-1.0.0.dist-info/METADATA
akshat_preprocessing-1.0.0.dist-info/WHEEL
akshat_preprocessing-1.0.0.dist-info/top_level.txt
akshat_preprocessing-1.0.0.dist-info/RECORD
