Metadata-Version: 2.1
Name: akshat-preprocessing
Version: 1.0.0
Summary: Data Preprocessing for Model Building
Home-page: UNKNOWN
Author: AKSHAT PANT
Author-email: akshat.pant06@gmail.com
License: UNKNOWN
Keywords: python,preprocess,data,EDA
Platform: UNKNOWN
Classifier: Development Status :: 1 - Planning
Classifier: Intended Audience :: Developers
Classifier: Programming Language :: Python :: 3
Classifier: Operating System :: Unix
Classifier: Operating System :: MacOS :: MacOS X
Classifier: Operating System :: Microsoft :: Windows
Requires-Dist: sklearn
Requires-Dist: pandas
